pygameplusplus-0.0.2.dist-info/licenses/LICENSE
pygamepp/__init__.py
pygamepp/colors.py
pygamepp/errors.py
pygamepp/keys.py
pygameplusplus-0.0.2.dist-info/METADATA
pygameplusplus-0.0.2.dist-info/WHEEL
pygameplusplus-0.0.2.dist-info/top_level.txt
pygameplusplus-0.0.2.dist-info/RECORD
