Metadata-Version: 2.4
Name: pygameplusplus
Version: 0.0.2
Summary: Better pygame
Home-page: https://github.com/yourusername/pygameplusplus
Author: Annes
Classifier: Programming Language :: Python :: 3
Classifier: Operating System :: OS Independent
Requires-Python: >=3.7
License-File: LICENSE
Requires-Dist: pygame
Requires-Dist: cairosvg
Dynamic: author
Dynamic: classifier
Dynamic: description
Dynamic: description-content-type
Dynamic: home-page
Dynamic: license-file
Dynamic: requires-dist
Dynamic: requires-python
Dynamic: summary
